pi_LCD/__init__.py
pi_LCD/pi_LCD.py
pi_LCD-0.0.1.dist-info/LICENSE
pi_LCD-0.0.1.dist-info/METADATA
pi_LCD-0.0.1.dist-info/WHEEL
pi_LCD-0.0.1.dist-info/top_level.txt
pi_LCD-0.0.1.dist-info/RECORD
