Metadata-Version: 2.1
Name: pi-LCD
Version: 0.0.1
Summary: LCD Interfacing
Home-page: UNKNOWN
Author: Ashish Sharma
Author-email: ashishbhardwaj023@gmail.com
License: UNKNOWN
Platform: UNKNOWN
Classifier: Programming Language :: Python :: 3
Classifier: License :: OSI Approved :: MIT License
Classifier: Operating System :: OS Independent
Requires-Python: >=3.0
